mimo/__init__.py
mimo/factory.py
mimo/gateway.py
mimo/message.py
mimo/sender.py
mimo/tools.py
mimosms-2.0.5.dist-info/LICENSE
mimosms-2.0.5.dist-info/METADATA
mimosms-2.0.5.dist-info/WHEEL
mimosms-2.0.5.dist-info/top_level.txt
mimosms-2.0.5.dist-info/RECORD
