Metadata-Version: 2.1
Name: mimosms
Version: 2.0.5
Summary: Integration with Mimo SMS API
Author-email: João Santos <josan5368@gmail.com>
License: MIT License
Project-URL: Homepage, https://github.com/jocaetano1/python-mimo-sms
Keywords: mimosms,sms
Classifier: License :: OSI Approved :: MIT License
Classifier: Programming Language :: Python
Classifier: Programming Language :: Python :: 3
Requires-Python: >=3.9
License-File: LICENSE
Requires-Dist: requests ==2.28.1
